nb_util/__init__.py
nb_util-0.0.1.dist-info/LICENSE
nb_util-0.0.1.dist-info/METADATA
nb_util-0.0.1.dist-info/WHEEL
nb_util-0.0.1.dist-info/top_level.txt
nb_util-0.0.1.dist-info/RECORD
