Metadata-Version: 2.1
Name: nb-util
Version: 0.0.1
Summary: A simple wrapper around joblib for jupyter notebooks
Home-page: https://github.com/jvansan/nb_util
Author: jvansan
Author-email: jeffreyavansanten@gmail.com
License: UNKNOWN
Platform: UNKNOWN
Classifier: Programming Language :: Python :: 3
Classifier: License :: OSI Approved :: MIT License
Classifier: Operating System :: OS Independent
Requires-Python: >=3.6
Requires-Dist: caffeine
Requires-Dist: tqdm
Requires-Dist: joblib
